snaptimer/__init__.py
snaptimer/snaptimer.py
snaptimer-0.0.5.dist-info/LICENSE
snaptimer-0.0.5.dist-info/METADATA
snaptimer-0.0.5.dist-info/WHEEL
snaptimer-0.0.5.dist-info/top_level.txt
snaptimer-0.0.5.dist-info/RECORD
