Metadata-Version: 2.1
Name: snaptimer
Version: 0.0.5
Summary: A colorful timer which handling basic information and allow to add info manually.Note: the version was migrated into module ronchang
Home-page: https://github.com/Ron-Chang/ronchang
Author: Ron Chang
Author-email: ron.hsien.chang@gmail.com
License: MIT
Platform: UNKNOWN
Requires-Python: >=3.6
Requires-Dist: colorama (==0.4.3)
